README.md
setup.cfg
setup.py
aioconcurrency/__init__.py
aioconcurrency.egg-info/PKG-INFO
aioconcurrency.egg-info/SOURCES.txt
aioconcurrency.egg-info/dependency_links.txt
aioconcurrency.egg-info/not-zip-safe
aioconcurrency.egg-info/top_level.txt
test/test_main.py