Metadata-Version: 2.1
Name: aioconcurrency
Version: 0.4.1
Summary: Run a coroutine with each item in an iterable, concurrently
Home-page: http://github.com/dflupu/aioconcurrency
Author: Daniel Lupu
Author-email: dflupu@gmail.com
License: MIT
Keywords: asyncio aio each map limit semaphore concurrency generator synchronization
Platform: UNKNOWN
